braces/__init__.py
braces/forms.py
braces/views/__init__.py
braces/views/_access.py
braces/views/_ajax.py
braces/views/_forms.py
braces/views/_other.py
braces/views/_queries.py
django_braces-1.16.0.dist-info/LICENSE
django_braces-1.16.0.dist-info/METADATA
django_braces-1.16.0.dist-info/WHEEL
django_braces-1.16.0.dist-info/top_level.txt
django_braces-1.16.0.dist-info/RECORD
